bracex/__init__.py
bracex/__main__.py
bracex/__meta__.py
bracex/py.typed
bracex-2.3.dist-info/METADATA
bracex-2.3.dist-info/WHEEL
bracex-2.3.dist-info/entry_points.txt
bracex-2.3.dist-info/license_files/LICENSE.md
bracex-2.3.dist-info/RECORD
