Metadata-Version: 2.1
Name: bracex
Version: 2.3
Summary: Bash style brace expander.
Project-URL: Homepage, https://github.com/facelessuser/bracex
Author-email: Isaac Muse <Isaac.Muse@gmail.com>
Keywords: bash,brace,expand
Classifier: Development Status :: 5 - Production/Stable
Classifier: Environment :: Console
Classifier: Intended Audience :: Developers
Classifier: License :: OSI Approved :: MIT License
Classifier: Operating System :: OS Independent
Classifier: Programming Language :: Python :: 3
Classifier: Programming Language :: Python :: 3.10
Classifier: Programming Language :: Python :: 3.7
Classifier: Programming Language :: Python :: 3.8
Classifier: Programming Language :: Python :: 3.9
Classifier: Topic :: Software Development :: Libraries :: Python Modules
Classifier: Typing :: Typed
Requires-Python: >=3.7
